Metadata-Version: 2.1
Name: molang
Version: 0.0.3
Summary: Molang to Python Translator & interpreter written in pure Python.
Home-page: https://github.com/legopitstop/molang/
Author: Legopitstop
Author-email: contact@lpsmods.dev
License: MIT
Project-URL: Download, https://github.com/legopitstop/molang/releases
Project-URL: Documentation, https://docs.lpsmods.dev/molang/
Project-URL: Source Code, https://github.com/legopitstop/molang
Keywords: Minecraft: Bedrock Edition,molang,language
Classifier: Development Status :: 4 - Beta
Classifier: Intended Audience :: Developers
Classifier: License :: OSI Approved :: MIT License
Classifier: Programming Language :: Python :: 3.12
Requires-Python: >=3.8
Provides-Extra: testing
License-File: LICENSE
